pyartnet/__init__.py
pyartnet/__version__.py
pyartnet/base/__init__.py
pyartnet/base/background_task.py
pyartnet/base/base_node.py
pyartnet/base/channel.py
pyartnet/base/channel_fade.py
pyartnet/base/network.py
pyartnet/base/output_correction.py
pyartnet/base/seq_counter.py
pyartnet/base/universe.py
pyartnet/errors.py
pyartnet/fades/__init__.py
pyartnet/fades/fade_base.py
pyartnet/fades/fade_linear.py
pyartnet/impl_artnet/__init__.py
pyartnet/impl_artnet/node.py
pyartnet/impl_artnet/universe.py
pyartnet/impl_kinet/__init__.py
pyartnet/impl_kinet/node.py
pyartnet/impl_kinet/universe.py
pyartnet/impl_sacn/__init__.py
pyartnet/impl_sacn/node.py
pyartnet/impl_sacn/universe.py
pyartnet/output_correction.py
pyartnet/py.typed
pyartnet-2.0.dist-info/WHEEL
pyartnet-2.0.dist-info/METADATA
pyartnet-2.0.dist-info/RECORD
