Metadata-Version: 2.4
Name: pyartnet
Version: 2.0
Summary: Python wrappers for the Art-Net protocol to send DMX over Ethernet
Keywords: DMX,Art-Net,ArtNet,sACN,E1.31,KiNet
Author: spaceman_spiff
License-Expression: GPL-3.0-or-later
Classifier: Development Status :: 5 - Production/Stable
Classifier: Programming Language :: Python :: 3.8
Classifier: Programming Language :: Python :: 3.9
Classifier: Programming Language :: Python :: 3.10
Classifier: Programming Language :: Python :: 3.11
Classifier: Programming Language :: Python :: 3.12
Classifier: Programming Language :: Python :: 3.13
Classifier: Programming Language :: Python :: 3.14
Classifier: Programming Language :: Python :: 3 :: Only
Classifier: License :: OSI Approved :: GNU General Public License v3 or later (GPLv3+)
Classifier: Operating System :: OS Independent
Requires-Dist: typing-extensions
Requires-Python: >=3.8
Project-URL: Documentation, https://pyartnet.readthedocs.io
Project-URL: Issues, https://github.com/spacemanspiff2007/PyArtNet/issues
Project-URL: Repository, https://github.com/spacemanspiff2007/PyArtNet'
